convert_md_to_rt-0.6.0.dist-info/licenses/LICENSE
md2rt/__init__.py
md2rt/clipboard.py
md2rt/converter.py
md2rt/detector.py
md2rt/menubar.py
md2rt/runner.py
convert_md_to_rt-0.6.0.dist-info/METADATA
convert_md_to_rt-0.6.0.dist-info/WHEEL
convert_md_to_rt-0.6.0.dist-info/entry_points.txt
convert_md_to_rt-0.6.0.dist-info/top_level.txt
convert_md_to_rt-0.6.0.dist-info/RECORD
