Metadata-Version: 2.4
Name: convert-md-to-rt
Version: 0.6.0
Summary: macOS clipboard tool that converts Markdown to rich text formatting
Author-email: Talib Kareem <taazkareem@icloud.com>
License: MIT
Keywords: markdown,rich-text,clipboard,macos,menubar,text-conversion,productivity-tool,developer-tool,python,pypi,formatting,editor,automation,clickup
Classifier: Development Status :: 4 - Beta
Classifier: Intended Audience :: End Users/Desktop
Classifier: License :: OSI Approved :: MIT License
Classifier: Operating System :: MacOS
Classifier: Programming Language :: Python :: 3
Classifier: Programming Language :: Python :: 3.9
Classifier: Programming Language :: Python :: 3.10
Classifier: Programming Language :: Python :: 3.11
Classifier: Programming Language :: Python :: 3.12
Classifier: Topic :: Desktop Environment
Classifier: Topic :: Text Processing :: Markup
Classifier: Topic :: Utilities
Requires-Python: >=3.9
License-File: LICENSE
Requires-Dist: pyobjc>=10.0
Requires-Dist: rumps>=0.4.0
Provides-Extra: dev
Requires-Dist: pytest>=7.0; extra == "dev"
Dynamic: license-file
